cloudshell/__init__.py
cloudshell/helpers/__init__.py
cloudshell/helpers/app_import/__init__.py
cloudshell/helpers/app_import/build_app_xml.py
cloudshell/helpers/app_import/images.py
cloudshell/helpers/app_import/upload_app_xml.py
cloudshell/helpers/save_workflow/__init__.py
cloudshell/helpers/save_workflow/deploy_info.py
cloudshell/helpers/save_workflow/extract_app_name.py
cloudshell/helpers/save_workflow/save_app_info_orch.py
cloudshell/helpers/save_workflow/save_app_utility.py
cloudshell_app_helper-2.0.4.dist-info/LICENSE
cloudshell_app_helper-2.0.4.dist-info/METADATA
cloudshell_app_helper-2.0.4.dist-info/WHEEL
cloudshell_app_helper-2.0.4.dist-info/top_level.txt
cloudshell_app_helper-2.0.4.dist-info/RECORD
