Metadata-Version: 2.1
Name: cloudshell-app-helper
Version: 2.0.4
Summary: CloudShell package to assist with creating Apps.
Home-page: UNKNOWN
Author: Quali
Author-email: support@qualisystems.com
License: UNKNOWN
Platform: UNKNOWN
Classifier: Programming Language :: Python :: 2.7
Classifier: License :: OSI Approved :: Apache Software License
Requires-Dist: cloudshell-orch-core (<3.4.0.0,>=3.3.0.0)
Requires-Dist: cloudshell-automation-api (>=2020.2.0.0)
Requires-Dist: requests (==2.23.0)
